Loxoc.libs/libSDL2-2-00949601.0.so.0.3000.4
Loxoc-1.0.0.dev45.dist-info/LICENSE
Loxoc-1.0.0.dev45.dist-info/METADATA
Loxoc-1.0.0.dev45.dist-info/RECORD
Loxoc-1.0.0.dev45.dist-info/WHEEL
Loxoc-1.0.0.dev45.dist-info/top_level.txt
Loxoc/default_vertex.glsl
Loxoc/default_vertex_2D.glsl
Loxoc/core.cpython-38-x86_64-linux-gnu.so
Loxoc/default_fragment.glsl
Loxoc/core.pyi
Loxoc/core.pxd
Loxoc/MissingTexture.jpg
Loxoc/default_fragment_2D.glsl
Loxoc/default_fragment_text.glsl
Loxoc/__init__.py
Loxoc/default_vertex_animated.glsl
Loxoc/core.pyx
Loxoc/default_particle.png
Loxoc/default_fragment_skybox.glsl
Loxoc/default_fragment_particle.glsl
Loxoc/default_vertex_particle.glsl
Loxoc/default_vertex_skybox.glsl
Loxoc/default_geometry_particle.glsl
Loxoc/default_vertex_text.glsl
