Metadata-Version: 2.1
Name: Loxoc
Version: 1.0.0.dev45
Summary: Loxoc is a flexible, straight forward, multi-paradigm game engine that is built from the ground up with developer experience in mind.  Utilizing a game loop system similar to pygame, you are able to abstract elements of your game away from the game loop as much as you'd like.
Author: William Lim
License: MIT
Project-URL: Documentation, https://frewtypebbles.github.io/
Project-URL: Bug Reports, https://github.com/FrewtyPebbles/Loxoc-Python3D-Game-Engine/issues
Project-URL: Source, https://github.com/FrewtyPebbles/Loxoc-Python3D-Game-Engine
Keywords: game engine sdl opengl 3d quaternion glm vec3 vector3
Classifier: Development Status :: 2 - Pre-Alpha
Classifier: License :: OSI Approved :: MIT License
Classifier: Intended Audience :: Developers
Classifier: Topic :: Games/Entertainment
License-File: LICENSE
